<?xml version="1.0" encoding="utf-8" standalone="no"?>
<billStatus>
  <bill>
    <billNumber>1220</billNumber>
    <createDate>2021-04-20T04:27:16Z</createDate>
    <updateDate>2022-02-09T12:35:46Z</updateDate>
    <originChamber>Senate</originChamber>
    <billType>S</billType>
    <introducedDate>2021-04-19</introducedDate>
    <congress>117</congress>
    <recordedVotes/>
    <committees>
      <billCommittees>
        <item>
          <systemCode>ssva00</systemCode>
          <name>Veterans' Affairs Committee</name>
          <chamber>Senate</chamber>
          <type>Standing</type>
          <subcommittees/>
          <activities>
            <item>
              <name>Markup by</name>
              <date>2021-07-28T15:30:14Z</date>
            </item>
            <item>
              <name>Hearings by</name>
              <date>2021-06-23T19:00:04Z</date>
            </item>
            <item>
              <name>Referred to</name>
              <date>2021-04-19T22:51:54Z</date>
            </item>
          </activities>
        </item>
      </billCommittees>
    </committees>
    <committeeReports/>
    <relatedBills>
      <item>
        <latestTitle>United States Cadet Nurse Corps Service Recognition Act of 2021</latestTitle>
        <congress>117</congress>
        <number>2568</number>
        <type>HR</type>
        <latestAction>
          <actionDate>2021-10-20</actionDate>
          <text>Subcommittee Hearings Held.</text>
        </latestAction>
        <relationshipDetails>
          <item>
            <type>Related bill</type>
            <identifiedBy>CRS</identifiedBy>
          </item>
        </relationshipDetails>
      </item>
    </relatedBills>
    <actions>
      <item>
        <actionDate>2021-07-28</actionDate>
        <committees>
          <item>
            <systemCode>ssva00</systemCode>
            <name>Veterans' Affairs Committee</name>
          </item>
        </committees>
        <links/>
        <sourceSystem>
          <code>0</code>
          <name>Senate</name>
        </sourceSystem>
        <text>Committee on Veterans' Affairs. Ordered to be reported without amendment favorably.</text>
        <type>Committee</type>
      </item>
      <item>
        <actionDate>2021-06-23</actionDate>
        <committees>
          <item>
            <systemCode>ssva00</systemCode>
            <name>Veterans' Affairs Committee</name>
          </item>
        </committees>
        <links/>
        <sourceSystem>
          <code>0</code>
          <name>Senate</name>
        </sourceSystem>
        <text>Committee on Veterans' Affairs. Hearings held.</text>
        <type>Committee</type>
      </item>
      <item>
        <actionDate>2021-04-19</actionDate>
        <committees>
          <item>
            <systemCode>ssva00</systemCode>
            <name>Veterans' Affairs Committee</name>
          </item>
        </committees>
        <links/>
        <sourceSystem>
          <code>0</code>
          <name>Senate</name>
        </sourceSystem>
        <text>Read twice and referred to the Committee on Veterans' Affairs.</text>
        <type>IntroReferral</type>
      </item>
      <item>
        <actionDate>2021-04-19</actionDate>
        <links/>
        <text>Introduced in Senate</text>
        <type>IntroReferral</type>
        <actionCode>10000</actionCode>
        <sourceSystem>
          <code>9</code>
          <name>Library of Congress</name>
        </sourceSystem>
        <committees/>
      </item>
      <actionTypeCounts>
        <orderedReported>1</orderedReported>
        <hearingsHeld>1</hearingsHeld>
        <referredToCommittee>1</referredToCommittee>
        <introducedInSenate>1</introducedInSenate>
      </actionTypeCounts>
      <actionByCounts>
        <senate>4</senate>
      </actionByCounts>
    </actions>
    <sponsors>
      <item>
        <bioguideId>W000817</bioguideId>
        <fullName>Sen. Warren, Elizabeth [D-MA]</fullName>
        <firstName>Elizabeth</firstName>
        <middleName>A.</middleName>
        <lastName>Warren</lastName>
        <party>D</party>
        <state>MA</state>
        <identifiers>
          <lisID>2182</lisID>
          <bioguideId>W000817</bioguideId>
          <gpoId/>
        </identifiers>
        <byRequestType/>
      </item>
    </sponsors>
    <cosponsors>
      <item>
        <bioguideId>C001035</bioguideId>
        <fullName>Sen. Collins, Susan M. [R-ME]</fullName>
        <firstName>Susan</firstName>
        <middleName>M.</middleName>
        <lastName>Collins</lastName>
        <party>R</party>
        <state>ME</state>
        <identifiers>
          <lisID>1541</lisID>
          <bioguideId>C001035</bioguideId>
          <gpoId>8291</gpoId>
        </identifiers>
        <sponsorshipDate>2021-04-19</sponsorshipDate>
        <isOriginalCosponsor>True</isOriginalCosponsor>
        <sponsorshipWithdrawnDate/>
      </item>
      <item>
        <bioguideId>K000383</bioguideId>
        <fullName>Sen. King, Angus S., Jr. [I-ME]</fullName>
        <firstName>Angus</firstName>
        <middleName>S.</middleName>
        <lastName>King</lastName>
        <party>I</party>
        <state>ME</state>
        <identifiers>
          <lisID>2185</lisID>
          <bioguideId>K000383</bioguideId>
          <gpoId/>
        </identifiers>
        <sponsorshipDate>2021-04-19</sponsorshipDate>
        <isOriginalCosponsor>True</isOriginalCosponsor>
        <sponsorshipWithdrawnDate/>
      </item>
      <item>
        <bioguideId>D000618</bioguideId>
        <fullName>Sen. Daines, Steve [R-MT]</fullName>
        <firstName>Steve</firstName>
        <middleName/>
        <lastName>Daines</lastName>
        <party>R</party>
        <state>MT</state>
        <identifiers>
          <lisID>2138</lisID>
          <bioguideId>D000618</bioguideId>
          <gpoId/>
        </identifiers>
        <sponsorshipDate>2021-04-19</sponsorshipDate>
        <isOriginalCosponsor>True</isOriginalCosponsor>
        <sponsorshipWithdrawnDate/>
      </item>
      <item>
        <bioguideId>M000639</bioguideId>
        <fullName>Sen. Menendez, Robert [D-NJ]</fullName>
        <firstName>Robert</firstName>
        <middleName/>
        <lastName>Menendez</lastName>
        <party>D</party>
        <state>NJ</state>
        <identifiers>
          <lisID>791</lisID>
          <bioguideId>M000639</bioguideId>
          <gpoId>8239</gpoId>
        </identifiers>
        <sponsorshipDate>2021-04-19</sponsorshipDate>
        <isOriginalCosponsor>True</isOriginalCosponsor>
        <sponsorshipWithdrawnDate/>
      </item>
      <item>
        <bioguideId>T000464</bioguideId>
        <fullName>Sen. Tester, Jon [D-MT]</fullName>
        <firstName>Jon</firstName>
        <middleName/>
        <lastName>Tester</lastName>
        <party>D</party>
        <state>MT</state>
        <identifiers>
          <lisID>1829</lisID>
          <bioguideId>T000464</bioguideId>
          <gpoId>8258</gpoId>
        </identifiers>
        <sponsorshipDate>2021-04-19</sponsorshipDate>
        <isOriginalCosponsor>True</isOriginalCosponsor>
        <sponsorshipWithdrawnDate/>
      </item>
      <item>
        <bioguideId>H001061</bioguideId>
        <fullName>Sen. Hoeven, John [R-ND]</fullName>
        <firstName>John</firstName>
        <middleName/>
        <lastName>Hoeven</lastName>
        <party>R</party>
        <state>ND</state>
        <identifiers>
          <lisID>2079</lisID>
          <bioguideId>H001061</bioguideId>
          <gpoId>8331</gpoId>
        </identifiers>
        <sponsorshipDate>2021-04-19</sponsorshipDate>
        <isOriginalCosponsor>True</isOriginalCosponsor>
        <sponsorshipWithdrawnDate/>
      </item>
      <item>
        <bioguideId>K000367</bioguideId>
        <fullName>Sen. Klobuchar, Amy [D-MN]</fullName>
        <firstName>Amy</firstName>
        <middleName/>
        <lastName>Klobuchar</lastName>
        <party>D</party>
        <state>MN</state>
        <identifiers>
          <lisID>1826</lisID>
          <bioguideId>K000367</bioguideId>
          <gpoId>8249</gpoId>
        </identifiers>
        <sponsorshipDate>2021-04-19</sponsorshipDate>
        <isOriginalCosponsor>True</isOriginalCosponsor>
        <sponsorshipWithdrawnDate/>
      </item>
      <item>
        <bioguideId>B001277</bioguideId>
        <fullName>Sen. Blumenthal, Richard [D-CT]</fullName>
        <firstName>Richard</firstName>
        <middleName/>
        <lastName>Blumenthal</lastName>
        <party>D</party>
        <state>CT</state>
        <identifiers>
          <lisID>2076</lisID>
          <bioguideId>B001277</bioguideId>
          <gpoId>8332</gpoId>
        </identifiers>
        <sponsorshipDate>2021-04-19</sponsorshipDate>
        <isOriginalCosponsor>True</isOriginalCosponsor>
        <sponsorshipWithdrawnDate/>
      </item>
      <item>
        <bioguideId>B000944</bioguideId>
        <fullName>Sen. Brown, Sherrod [D-OH]</fullName>
        <firstName>Sherrod</firstName>
        <middleName/>
        <lastName>Brown</lastName>
        <party>D</party>
        <state>OH</state>
        <identifiers>
          <lisID>136</lisID>
          <bioguideId>B000944</bioguideId>
          <gpoId>8309</gpoId>
        </identifiers>
        <sponsorshipDate>2021-04-19</sponsorshipDate>
        <isOriginalCosponsor>True</isOriginalCosponsor>
        <sponsorshipWithdrawnDate/>
      </item>
      <item>
        <bioguideId>M001176</bioguideId>
        <fullName>Sen. Merkley, Jeff [D-OR]</fullName>
        <firstName>Jeff</firstName>
        <middleName/>
        <lastName>Merkley</lastName>
        <party>D</party>
        <state>OR</state>
        <identifiers>
          <lisID>1900</lisID>
          <bioguideId>M001176</bioguideId>
          <gpoId>8238</gpoId>
        </identifiers>
        <sponsorshipDate>2021-04-19</sponsorshipDate>
        <isOriginalCosponsor>True</isOriginalCosponsor>
        <sponsorshipWithdrawnDate/>
      </item>
      <item>
        <bioguideId>M000133</bioguideId>
        <fullName>Sen. Markey, Edward J. [D-MA]</fullName>
        <firstName>Edward</firstName>
        <middleName>J.</middleName>
        <lastName>Markey</lastName>
        <party>D</party>
        <state>MA</state>
        <identifiers>
          <lisID>735</lisID>
          <bioguideId>M000133</bioguideId>
          <gpoId>7972</gpoId>
        </identifiers>
        <sponsorshipDate>2021-04-19</sponsorshipDate>
        <isOriginalCosponsor>True</isOriginalCosponsor>
        <sponsorshipWithdrawnDate/>
      </item>
      <item>
        <bioguideId>S000770</bioguideId>
        <fullName>Sen. Stabenow, Debbie [D-MI]</fullName>
        <firstName>Debbie</firstName>
        <middleName/>
        <lastName>Stabenow</lastName>
        <party>D</party>
        <state>MI</state>
        <identifiers>
          <lisID>1531</lisID>
          <bioguideId>S000770</bioguideId>
          <gpoId>8261</gpoId>
        </identifiers>
        <sponsorshipDate>2021-04-19</sponsorshipDate>
        <isOriginalCosponsor>True</isOriginalCosponsor>
        <sponsorshipWithdrawnDate/>
      </item>
      <item>
        <bioguideId>W000779</bioguideId>
        <fullName>Sen. Wyden, Ron [D-OR]</fullName>
        <firstName>Ron</firstName>
        <middleName/>
        <lastName>Wyden</lastName>
        <party>D</party>
        <state>OR</state>
        <identifiers>
          <lisID>1247</lisID>
          <bioguideId>W000779</bioguideId>
          <gpoId>8265</gpoId>
        </identifiers>
        <sponsorshipDate>2021-04-19</sponsorshipDate>
        <isOriginalCosponsor>True</isOriginalCosponsor>
        <sponsorshipWithdrawnDate/>
      </item>
      <item>
        <bioguideId>C001096</bioguideId>
        <fullName>Sen. Cramer, Kevin [R-ND]</fullName>
        <firstName>Kevin</firstName>
        <middleName/>
        <lastName>Cramer</lastName>
        <party>R</party>
        <state>ND</state>
        <identifiers>
          <lisID>2144</lisID>
          <bioguideId>C001096</bioguideId>
          <gpoId/>
        </identifiers>
        <sponsorshipDate>2021-04-19</sponsorshipDate>
        <isOriginalCosponsor>True</isOriginalCosponsor>
        <sponsorshipWithdrawnDate/>
      </item>
      <item>
        <bioguideId>B001230</bioguideId>
        <fullName>Sen. Baldwin, Tammy [D-WI]</fullName>
        <firstName>Tammy</firstName>
        <middleName/>
        <lastName>Baldwin</lastName>
        <party>D</party>
        <state>WI</state>
        <identifiers>
          <lisID>1558</lisID>
          <bioguideId>B001230</bioguideId>
          <gpoId>8215</gpoId>
        </identifiers>
        <sponsorshipDate>2021-04-19</sponsorshipDate>
        <isOriginalCosponsor>True</isOriginalCosponsor>
        <sponsorshipWithdrawnDate/>
      </item>
      <item>
        <bioguideId>M001111</bioguideId>
        <fullName>Sen. Murray, Patty [D-WA]</fullName>
        <firstName>Patty</firstName>
        <middleName/>
        <lastName>Murray</lastName>
        <party>D</party>
        <state>WA</state>
        <identifiers>
          <lisID>1409</lisID>
          <bioguideId>M001111</bioguideId>
          <gpoId>8237</gpoId>
        </identifiers>
        <sponsorshipDate>2021-04-19</sponsorshipDate>
        <isOriginalCosponsor>True</isOriginalCosponsor>
        <sponsorshipWithdrawnDate/>
      </item>
      <item>
        <bioguideId>C001070</bioguideId>
        <fullName>Sen. Casey, Robert P., Jr. [D-PA]</fullName>
        <firstName>Bob</firstName>
        <middleName/>
        <lastName>Casey</lastName>
        <party>D</party>
        <state>PA</state>
        <identifiers>
          <lisID>1828</lisID>
          <bioguideId>C001070</bioguideId>
          <gpoId>8282</gpoId>
        </identifiers>
        <sponsorshipDate>2021-04-19</sponsorshipDate>
        <isOriginalCosponsor>True</isOriginalCosponsor>
        <sponsorshipWithdrawnDate/>
      </item>
      <item>
        <bioguideId>C001075</bioguideId>
        <fullName>Sen. Cassidy, Bill [R-LA]</fullName>
        <firstName>Bill</firstName>
        <middleName/>
        <lastName>Cassidy</lastName>
        <party>R</party>
        <state>LA</state>
        <identifiers>
          <lisID>1925</lisID>
          <bioguideId>C001075</bioguideId>
          <gpoId>7964</gpoId>
        </identifiers>
        <sponsorshipDate>2021-04-19</sponsorshipDate>
        <isOriginalCosponsor>True</isOriginalCosponsor>
        <sponsorshipWithdrawnDate/>
      </item>
      <item>
        <bioguideId>B001236</bioguideId>
        <fullName>Sen. Boozman, John [R-AR]</fullName>
        <firstName>John</firstName>
        <middleName/>
        <lastName>Boozman</lastName>
        <party>R</party>
        <state>AR</state>
        <identifiers>
          <lisID>1687</lisID>
          <bioguideId>B001236</bioguideId>
          <gpoId>8247</gpoId>
        </identifiers>
        <sponsorshipDate>2021-04-19</sponsorshipDate>
        <isOriginalCosponsor>True</isOriginalCosponsor>
        <sponsorshipWithdrawnDate/>
      </item>
      <item>
        <bioguideId>V000128</bioguideId>
        <fullName>Sen. Van Hollen, Chris [D-MD]</fullName>
        <firstName>Chris</firstName>
        <middleName/>
        <lastName>Van Hollen</lastName>
        <party>D</party>
        <state>MD</state>
        <identifiers>
          <lisID>1729</lisID>
          <bioguideId>V000128</bioguideId>
          <gpoId>7983</gpoId>
        </identifiers>
        <sponsorshipDate>2021-04-19</sponsorshipDate>
        <isOriginalCosponsor>True</isOriginalCosponsor>
        <sponsorshipWithdrawnDate/>
      </item>
      <item>
        <bioguideId>B001288</bioguideId>
        <fullName>Sen. Booker, Cory A. [D-NJ]</fullName>
        <firstName>Cory</firstName>
        <middleName/>
        <lastName>Booker</lastName>
        <party>D</party>
        <state>NJ</state>
        <identifiers>
          <lisID>2194</lisID>
          <bioguideId>B001288</bioguideId>
          <gpoId/>
        </identifiers>
        <sponsorshipDate>2021-06-21</sponsorshipDate>
        <isOriginalCosponsor>False</isOriginalCosponsor>
        <sponsorshipWithdrawnDate/>
      </item>
      <item>
        <bioguideId>L000174</bioguideId>
        <fullName>Sen. Leahy, Patrick J. [D-VT]</fullName>
        <firstName>Patrick</firstName>
        <middleName/>
        <lastName>Leahy</lastName>
        <party>D</party>
        <state>VT</state>
        <identifiers>
          <lisID>1383</lisID>
          <bioguideId>L000174</bioguideId>
          <gpoId>8244</gpoId>
        </identifiers>
        <sponsorshipDate>2021-06-22</sponsorshipDate>
        <isOriginalCosponsor>False</isOriginalCosponsor>
        <sponsorshipWithdrawnDate/>
      </item>
      <item>
        <bioguideId>L000570</bioguideId>
        <fullName>Sen. Lujan, Ben Ray [D-NM]</fullName>
        <firstName>Ben</firstName>
        <middleName>R.</middleName>
        <lastName>Lujan</lastName>
        <party>D</party>
        <state>NM</state>
        <identifiers>
          <lisID>1939</lisID>
          <bioguideId>L000570</bioguideId>
          <gpoId>8058</gpoId>
        </identifiers>
        <sponsorshipDate>2021-08-09</sponsorshipDate>
        <isOriginalCosponsor>False</isOriginalCosponsor>
        <sponsorshipWithdrawnDate/>
      </item>
      <item>
        <bioguideId>P000449</bioguideId>
        <fullName>Sen. Portman, Rob [R-OH]</fullName>
        <firstName>Rob</firstName>
        <middleName/>
        <lastName>Portman</lastName>
        <party>R</party>
        <state>OH</state>
        <identifiers>
          <lisID>924</lisID>
          <bioguideId>P000449</bioguideId>
          <gpoId>8266</gpoId>
        </identifiers>
        <sponsorshipDate>2021-10-27</sponsorshipDate>
        <isOriginalCosponsor>False</isOriginalCosponsor>
        <sponsorshipWithdrawnDate/>
      </item>
    </cosponsors>
    <cboCostEstimates>
      <item>
        <pubDate>2021-09-28T12:30:00Z</pubDate>
        <title>S. 1220, United States Cadet Nurse Corps Service Recognition Act of 2021</title>
        <url>https://www.cbo.gov/publication/57509</url>
      </item>
    </cboCostEstimates>
    <laws/>
    <notes/>
    <policyArea>
      <name>Armed Forces and National Security</name>
    </policyArea>
    <subjects>
      <billSubjects>
        <legislativeSubjects>
          <item>
            <name>Cemeteries and funerals</name>
          </item>
          <item>
            <name>Conflicts and wars</name>
          </item>
          <item>
            <name>Health personnel</name>
          </item>
          <item>
            <name>Military medicine</name>
          </item>
          <item>
            <name>Military personnel and dependents</name>
          </item>
          <item>
            <name>Monuments and memorials</name>
          </item>
          <item>
            <name>Nursing</name>
          </item>
          <item>
            <name>Veterans' organizations and recognition</name>
          </item>
        </legislativeSubjects>
        <policyArea>
          <name>Armed Forces and National Security</name>
        </policyArea>
      </billSubjects>
    </subjects>
    <summaries>
      <billSummaries>
        <item>
          <versionCode>00</versionCode>
          <actionDate>2021-04-19</actionDate>
          <actionDesc>Introduced in Senate</actionDesc>
          <lastSummaryUpdateDate>2022-01-20T16:18:14Z</lastSummaryUpdateDate>
          <text>
            <![CDATA[ <p><strong>United States Cadet Nurse Corps Service Recognition Act of 2021</strong></p> <p>This bill recognizes service as a member of the U.S. Cadet Nurse Corps between July 1, 1943, and December 31, 1948, as active duty service. The active duty designation entitles qualifying individuals to certain benefits afforded to veterans, such as burial benefits (not including internment at Arlington National Cemetery) and honorary veteran status.</p> <p>Under the bill, the Department of Defense (DOD) must issue individuals who served in the corps during the specified period a discharge from their service under honorable conditions if such a discharge is warranted based on the duration and nature of the service. </p> <p>Such individuals are not entitled to Department of Veterans Affairs benefits aside from those related to burials and memorials.</p> <p>The bill also authorizes DOD to produce a service medal or other commendation, memorial plaque, or grave marker to honor the individuals. </p>]]>
          </text>
          <updateDate>2021-04-19T04:00:00Z</updateDate>
          <name>Introduced in Senate</name>
        </item>
      </billSummaries>
    </summaries>
    <title>United States Cadet Nurse Corps Service Recognition Act of 2021</title>
    <titles>
      <item>
        <titleType>Display Title</titleType>
        <parentTitleType/>
        <title>United States Cadet Nurse Corps Service Recognition Act of 2021</title>
        <chamberCode/>
        <chamberName/>
      </item>
      <item>
        <titleType>Short Title(s) as Introduced</titleType>
        <parentTitleType>Short Title</parentTitleType>
        <title>United States Cadet Nurse Corps Service Recognition Act of 2021</title>
        <chamberCode/>
        <chamberName/>
      </item>
      <item>
        <titleType>Official Title as Introduced</titleType>
        <parentTitleType/>
        <title>A bill to amend title 38, United States Code, to recognize and honor the service of individuals who served in the United States Cadet Nurse Corps during World War II, and for other purposes.</title>
        <chamberCode/>
        <chamberName/>
      </item>
    </titles>
    <amendments/>
    <textVersions>
      <item>
        <type>Introduced in Senate</type>
        <date>2021-04-19T04:00:00Z</date>
        <formats>
          <item>
            <url>https://www.govinfo.gov/content/pkg/BILLS-117s1220is/xml/BILLS-117s1220is.xml</url>
          </item>
        </formats>
      </item>
    </textVersions>
    <latestAction>
      <actionDate>2021-07-28</actionDate>
      <text>Committee on Veterans' Affairs. Ordered to be reported without amendment favorably.</text>
      <links/>
    </latestAction>
    <calendarNumbers/>
    <version>1.0.0</version>
  </bill>
  <dublinCore xmlns:dc="http://purl.org/dc/elements/1.1/">
    <dc:format>text/xml</dc:format>
    <dc:language>EN</dc:language>
    <dc:rights>Pursuant to Title 17 Section 105 of the United States Code, this file is not subject to copyright protection and is in the public domain.</dc:rights>
    <dc:contributor>Congressional Research Service, Library of Congress</dc:contributor>
    <dc:description>This file contains bill summaries and statuses for federal legislation. A bill summary describes the most significant provisions of a piece of legislation and details the effects the legislative text may have on current law and federal programs. Bill summaries are authored by the Congressional Research Service (CRS) of the Library of Congress. As stated in Public Law 91-510 (2 USC 166 (d)(6)), one of the duties of CRS is "to prepare summaries and digests of bills and resolutions of a public general nature introduced in the Senate or House of Representatives". For more information, refer to the User Guide that accompanies this file.</dc:description>
  </dublinCore>
</billStatus>
